setup.py
supertoolbox/Emails.py
supertoolbox/LICENSE
supertoolbox/Test.py
supertoolbox/__init__.py
supertoolbox.egg-info/PKG-INFO
supertoolbox.egg-info/SOURCES.txt
supertoolbox.egg-info/dependency_links.txt
supertoolbox.egg-info/top_level.txt