Metadata-Version: 2.1
Name: supertoolbox
Version: 0.0.1
Summary: The super supertoolbox makes the code simpler!
Home-page: https://github.com/YouAreOnlyOne
Author: Frank YCJ
Author-email: 1320259466@qq.com
License: Apache 2.0 license
Project-URL: Bug Tracker, https://github.com/YouAreOnlyOne/FastFrameJar/issues
Project-URL: Documentation, https://github.com/YouAreOnlyOne/FastFrameJar
Project-URL: Source Code, https://github.com/YouAreOnlyOne/FastFrameJar
Keywords: tool util code simpler box
Platform: UNKNOWN
Classifier: Programming Language :: Python :: 2
Classifier: License :: OSI Approved :: MIT License
Classifier: Operating System :: OS Independent
Requires-Python: >=2.6, !=3.0.*, !=3.1.*, !=3.2.*, !=3.3.*, !=3.4.*
